{"name":"search  for a automation course","id":"academy-choucair;search--for-a-automation-course","testSteps":[{"number":1,"description":"Given than Cindy wants to learn automation at the academy Choucair","duration":16960,"startTime":"2021-07-21T23:40:25.106-05:00[America/Bogota]","screenshots":[{"screenshot":"6ec9f22276545844bcd02a1b2f85c55314712094936a66129e0d44f20fbd924c.png","timeStamp":1626928842066}],"result":"SUCCESS","precondition":false,"level":0,"lineNumber":0,"children":[{"number":2,"description":"Cindy open up","duration":8281,"startTime":"2021-07-21T23:40:25.914-05:00[America/Bogota]","screenshots":[{"screenshot":"4af2f3beaacb40e55134868de19a06aa6ca8c20fab120bca660faaaec0498acd.png","timeStamp":1626928834195}],"result":"SUCCESS","precondition":false,"level":1,"lineNumber":0,"children":[{"number":3,"description":"Cindy opens the Choucair academypage","duration":8229,"startTime":"2021-07-21T23:40:25.943-05:00[America/Bogota]","screenshots":[{"screenshot":"4af2f3beaacb40e55134868de19a06aa6ca8c20fab120bca660faaaec0498acd.png","timeStamp":1626928834171}],"result":"SUCCESS","precondition":false,"level":2,"lineNumber":0}]},{"number":4,"description":"Cindy login","duration":7853,"startTime":"2021-07-21T23:40:34.197-05:00[America/Bogota]","screenshots":[{"screenshot":"6ec9f22276545844bcd02a1b2f85c55314712094936a66129e0d44f20fbd924c.png","timeStamp":1626928842050}],"result":"SUCCESS","precondition":false,"level":1,"lineNumber":0,"children":[{"number":5,"description":"Cindy clicks on button that show us the form to login","duration":939,"startTime":"2021-07-21T23:40:34.243-05:00[America/Bogota]","screenshots":[{"screenshot":"958e803c588002b9b807f016ff02442c0c52de10cb7cabf6a8c576db6c4a7047.png","timeStamp":1626928835182}],"result":"SUCCESS","precondition":false,"level":2,"lineNumber":0},{"number":6,"description":"Cindy enters \u00271035427106\u0027 into where do we write the user","duration":1151,"startTime":"2021-07-21T23:40:35.186-05:00[America/Bogota]","screenshots":[{"screenshot":"14f06abf339500373cfb8e7f17b84555e949ba599e93715b15e19ee77fb2f52f.png","timeStamp":1626928836337}],"result":"SUCCESS","precondition":false,"level":2,"lineNumber":0},{"number":7,"description":"Cindy enters \u0027Choucair2021*\u0027 into where do we write the password","duration":865,"startTime":"2021-07-21T23:40:36.339-05:00[America/Bogota]","screenshots":[{"screenshot":"a978d58b00e2353b2b959919ea587b9934e6ca2372fb9f32bbfd32f86c3fde49.png","timeStamp":1626928837204}],"result":"SUCCESS","precondition":false,"level":2,"lineNumber":0},{"number":8,"description":"Cindy clicks on button to confirm login","duration":4827,"startTime":"2021-07-21T23:40:37.206-05:00[America/Bogota]","screenshots":[{"screenshot":"6ec9f22276545844bcd02a1b2f85c55314712094936a66129e0d44f20fbd924c.png","timeStamp":1626928842033}],"result":"SUCCESS","precondition":false,"level":2,"lineNumber":0}]}]},{"number":9,"description":"When she search for the course Recursos Automatizacion Bancolombia on the Chaucair academy platform","duration":11733,"startTime":"2021-07-21T23:40:42.067-05:00[America/Bogota]","exception":{"errorType":"net.thucydides.core.webdriver.exceptions.ElementShouldBeEnabledException","message":"Expected enabled element was not enabled","stackTrace":[{"declaringClass":"co.com.choucair.certification.proyecto1.tasks.Search","methodName":"performAs","fileName":"Search.java","lineNumber":25},{"declaringClass":"co.com.choucair.certification.proyecto1.stepdefinitions.ChoucairAcademyStepDefinitions","methodName":"sheSearchForTheCourseRecursosAutomatizacionBancolombiaOnTheChaucairAcademyPlatform","fileName":"ChoucairAcademyStepDefinitions.java","lineNumber":28},{"declaringClass":"cucumber.runner.Runner","methodName":"runPickle","fileName":"Runner.java","lineNumber":80}],"rootCause":{"errorType":"org.openqa.selenium.TimeoutException","message":"Expected condition failed: waiting for By.id: coursesearchbox to be enabled (tried for 5 second(s) with 100 milliseconds interval)","stackTrace":[{"declaringClass":"co.com.choucair.certification.proyecto1.tasks.Search","methodName":"performAs","fileName":"Search.java","lineNumber":25},{"declaringClass":"co.com.choucair.certification.proyecto1.stepdefinitions.ChoucairAcademyStepDefinitions","methodName":"sheSearchForTheCourseRecursosAutomatizacionBancolombiaOnTheChaucairAcademyPlatform","fileName":"ChoucairAcademyStepDefinitions.java","lineNumber":28},{"declaringClass":"cucumber.runner.Runner","methodName":"runPickle","fileName":"Runner.java","lineNumber":80}],"rootCause":{"errorType":"org.openqa.selenium.NoSuchElementException","message":"no such element: Unable to locate element: {\"method\":\"css selector\",\"selector\":\"#coursesearchbox\"}\n  (Session info: chrome\u003d92.0.4515.107)\nFor documentation on this error, please visit: https://www.seleniumhq.org/exceptions/no_such_element.html\nBuild info: version: \u00273.141.59\u0027, revision: \u0027e82be7d358\u0027, time: \u00272018-11-14T08:17:03\u0027\nSystem info: host: \u0027SOPORTE_WEB\u0027, ip: \u0027172.26.64.1\u0027, os.name: \u0027Windows 10\u0027, os.arch: \u0027amd64\u0027, os.version: \u002710.0\u0027, java.version: \u00271.8.0_231\u0027\nDriver info: org.openqa.selenium.chrome.ChromeDriver\nCapabilities {acceptInsecureCerts: false, browserName: chrome, browserVersion: 92.0.4515.107, chrome: {chromedriverVersion: 92.0.4515.43 (8c61b7e2989f2..., userDataDir: C:\\Users\\DITOSA~1\\AppData\\L...}, goog:chromeOptions: {debuggerAddress: localhost:55690}, javascriptEnabled: true, networkConnectionEnabled: false, pageLoadStrategy: normal, platform: WINDOWS, platformName: WINDOWS, proxy: Proxy(), setWindowRect: true, strictFileInteractability: false, timeouts: {implicit: 0, pageLoad: 300000, script: 30000}, unhandledPromptBehavior: dismiss and notify, webauthn:extension:credBlob: true, webauthn:extension:largeBlob: true, webauthn:virtualAuthenticators: true}\nSession ID: dc7412c25d1b2d013648faf9aefe75d9\n*** Element info: {Using\u003did, value\u003dcoursesearchbox}","stackTrace":[{"declaringClass":"co.com.choucair.certification.proyecto1.tasks.Search","methodName":"performAs","fileName":"Search.java","lineNumber":25},{"declaringClass":"co.com.choucair.certification.proyecto1.stepdefinitions.ChoucairAcademyStepDefinitions","methodName":"sheSearchForTheCourseRecursosAutomatizacionBancolombiaOnTheChaucairAcademyPlatform","fileName":"ChoucairAcademyStepDefinitions.java","lineNumber":28},{"declaringClass":"cucumber.runner.Runner","methodName":"runPickle","fileName":"Runner.java","lineNumber":80}]}}},"result":"FAILURE","precondition":false,"level":0,"lineNumber":0,"children":[{"number":10,"description":"Cindy search","duration":11709,"startTime":"2021-07-21T23:40:42.079-05:00[America/Bogota]","exception":{"errorType":"net.thucydides.core.webdriver.exceptions.ElementShouldBeEnabledException","message":"Expected enabled element was not enabled","stackTrace":[{"declaringClass":"co.com.choucair.certification.proyecto1.tasks.Search","methodName":"performAs","fileName":"Search.java","lineNumber":25},{"declaringClass":"co.com.choucair.certification.proyecto1.stepdefinitions.ChoucairAcademyStepDefinitions","methodName":"sheSearchForTheCourseRecursosAutomatizacionBancolombiaOnTheChaucairAcademyPlatform","fileName":"ChoucairAcademyStepDefinitions.java","lineNumber":28},{"declaringClass":"cucumber.runner.Runner","methodName":"runPickle","fileName":"Runner.java","lineNumber":80}],"rootCause":{"errorType":"org.openqa.selenium.TimeoutException","message":"Expected condition failed: waiting for By.id: coursesearchbox to be enabled (tried for 5 second(s) with 100 milliseconds interval)","stackTrace":[{"declaringClass":"co.com.choucair.certification.proyecto1.tasks.Search","methodName":"performAs","fileName":"Search.java","lineNumber":25},{"declaringClass":"co.com.choucair.certification.proyecto1.stepdefinitions.ChoucairAcademyStepDefinitions","methodName":"sheSearchForTheCourseRecursosAutomatizacionBancolombiaOnTheChaucairAcademyPlatform","fileName":"ChoucairAcademyStepDefinitions.java","lineNumber":28},{"declaringClass":"cucumber.runner.Runner","methodName":"runPickle","fileName":"Runner.java","lineNumber":80}],"rootCause":{"errorType":"org.openqa.selenium.NoSuchElementException","message":"no such element: Unable to locate element: {\"method\":\"css selector\",\"selector\":\"#coursesearchbox\"}\n  (Session info: chrome\u003d92.0.4515.107)\nFor documentation on this error, please visit: https://www.seleniumhq.org/exceptions/no_such_element.html\nBuild info: version: \u00273.141.59\u0027, revision: \u0027e82be7d358\u0027, time: \u00272018-11-14T08:17:03\u0027\nSystem info: host: \u0027SOPORTE_WEB\u0027, ip: \u0027172.26.64.1\u0027, os.name: \u0027Windows 10\u0027, os.arch: \u0027amd64\u0027, os.version: \u002710.0\u0027, java.version: \u00271.8.0_231\u0027\nDriver info: org.openqa.selenium.chrome.ChromeDriver\nCapabilities {acceptInsecureCerts: false, browserName: chrome, browserVersion: 92.0.4515.107, chrome: {chromedriverVersion: 92.0.4515.43 (8c61b7e2989f2..., userDataDir: C:\\Users\\DITOSA~1\\AppData\\L...}, goog:chromeOptions: {debuggerAddress: localhost:55690}, javascriptEnabled: true, networkConnectionEnabled: false, pageLoadStrategy: normal, platform: WINDOWS, platformName: WINDOWS, proxy: Proxy(), setWindowRect: true, strictFileInteractability: false, timeouts: {implicit: 0, pageLoad: 300000, script: 30000}, unhandledPromptBehavior: dismiss and notify, webauthn:extension:credBlob: true, webauthn:extension:largeBlob: true, webauthn:virtualAuthenticators: true}\nSession ID: dc7412c25d1b2d013648faf9aefe75d9\n*** Element info: {Using\u003did, value\u003dcoursesearchbox}","stackTrace":[{"declaringClass":"co.com.choucair.certification.proyecto1.tasks.Search","methodName":"performAs","fileName":"Search.java","lineNumber":25},{"declaringClass":"co.com.choucair.certification.proyecto1.stepdefinitions.ChoucairAcademyStepDefinitions","methodName":"sheSearchForTheCourseRecursosAutomatizacionBancolombiaOnTheChaucairAcademyPlatform","fileName":"ChoucairAcademyStepDefinitions.java","lineNumber":28},{"declaringClass":"cucumber.runner.Runner","methodName":"runPickle","fileName":"Runner.java","lineNumber":80}]}}},"result":"FAILURE","precondition":false,"level":1,"lineNumber":0,"children":[{"number":11,"description":"Cindy clicks on select university","duration":1332,"startTime":"2021-07-21T23:40:42.116-05:00[America/Bogota]","screenshots":[{"screenshot":"2e59fb1d587d7ba7b70d5391edeb64c6b12dfaafb0794c2fc1bc9faf308a1cb1.png","timeStamp":1626928843448}],"result":"SUCCESS","precondition":false,"level":2,"lineNumber":0},{"number":12,"description":"Cindy enters \u0027\u0027 into course finder","duration":10317,"startTime":"2021-07-21T23:40:43.450-05:00[America/Bogota]","screenshots":[{"screenshot":"2e59fb1d587d7ba7b70d5391edeb64c6b12dfaafb0794c2fc1bc9faf308a1cb1.png","htmlSource":"pagesource3419863718811976135.html.txt","timeStamp":1626928853760}],"exception":{"errorType":"net.thucydides.core.webdriver.exceptions.ElementShouldBeEnabledException","message":"Expected enabled element was not enabled","stackTrace":[{"declaringClass":"co.com.choucair.certification.proyecto1.tasks.Search","methodName":"performAs","fileName":"Search.java","lineNumber":25},{"declaringClass":"co.com.choucair.certification.proyecto1.stepdefinitions.ChoucairAcademyStepDefinitions","methodName":"sheSearchForTheCourseRecursosAutomatizacionBancolombiaOnTheChaucairAcademyPlatform","fileName":"ChoucairAcademyStepDefinitions.java","lineNumber":28},{"declaringClass":"cucumber.runner.Runner","methodName":"runPickle","fileName":"Runner.java","lineNumber":80}],"rootCause":{"errorType":"org.openqa.selenium.TimeoutException","message":"Expected condition failed: waiting for By.id: coursesearchbox to be enabled (tried for 5 second(s) with 100 milliseconds interval)","stackTrace":[{"declaringClass":"co.com.choucair.certification.proyecto1.tasks.Search","methodName":"performAs","fileName":"Search.java","lineNumber":25},{"declaringClass":"co.com.choucair.certification.proyecto1.stepdefinitions.ChoucairAcademyStepDefinitions","methodName":"sheSearchForTheCourseRecursosAutomatizacionBancolombiaOnTheChaucairAcademyPlatform","fileName":"ChoucairAcademyStepDefinitions.java","lineNumber":28},{"declaringClass":"cucumber.runner.Runner","methodName":"runPickle","fileName":"Runner.java","lineNumber":80}],"rootCause":{"errorType":"org.openqa.selenium.NoSuchElementException","message":"no such element: Unable to locate element: {\"method\":\"css selector\",\"selector\":\"#coursesearchbox\"}\n  (Session info: chrome\u003d92.0.4515.107)\nFor documentation on this error, please visit: https://www.seleniumhq.org/exceptions/no_such_element.html\nBuild info: version: \u00273.141.59\u0027, revision: \u0027e82be7d358\u0027, time: \u00272018-11-14T08:17:03\u0027\nSystem info: host: \u0027SOPORTE_WEB\u0027, ip: \u0027172.26.64.1\u0027, os.name: \u0027Windows 10\u0027, os.arch: \u0027amd64\u0027, os.version: \u002710.0\u0027, java.version: \u00271.8.0_231\u0027\nDriver info: org.openqa.selenium.chrome.ChromeDriver\nCapabilities {acceptInsecureCerts: false, browserName: chrome, browserVersion: 92.0.4515.107, chrome: {chromedriverVersion: 92.0.4515.43 (8c61b7e2989f2..., userDataDir: C:\\Users\\DITOSA~1\\AppData\\L...}, goog:chromeOptions: {debuggerAddress: localhost:55690}, javascriptEnabled: true, networkConnectionEnabled: false, pageLoadStrategy: normal, platform: WINDOWS, platformName: WINDOWS, proxy: Proxy(), setWindowRect: true, strictFileInteractability: false, timeouts: {implicit: 0, pageLoad: 300000, script: 30000}, unhandledPromptBehavior: dismiss and notify, webauthn:extension:credBlob: true, webauthn:extension:largeBlob: true, webauthn:virtualAuthenticators: true}\nSession ID: dc7412c25d1b2d013648faf9aefe75d9\n*** Element info: {Using\u003did, value\u003dcoursesearchbox}","stackTrace":[{"declaringClass":"co.com.choucair.certification.proyecto1.tasks.Search","methodName":"performAs","fileName":"Search.java","lineNumber":25},{"declaringClass":"co.com.choucair.certification.proyecto1.stepdefinitions.ChoucairAcademyStepDefinitions","methodName":"sheSearchForTheCourseRecursosAutomatizacionBancolombiaOnTheChaucairAcademyPlatform","fileName":"ChoucairAcademyStepDefinitions.java","lineNumber":28},{"declaringClass":"cucumber.runner.Runner","methodName":"runPickle","fileName":"Runner.java","lineNumber":80}]}}},"result":"FAILURE","precondition":false,"level":2,"lineNumber":0}]}]},{"number":13,"description":"Then she finds the course called recursos Automatizacion Bancolombia","duration":2,"startTime":"2021-07-21T23:40:53.828-05:00[America/Bogota]","result":"SKIPPED","precondition":false,"level":0,"lineNumber":0}],"userStory":{"id":"academy-choucair","storyName":"Academy Choucair","path":"src/test/resources/features/academyChoucair.feature","narrative":"  As a user, i want to learn how to automate in screamplay at the choucair Academy with the automation course","type":"feature"},"featureTag":{"name":"Features/Academy Choucair","type":"feature","displayName":"Features/Academy Choucair"},"title":"search  for a automation course","tags":[{"name":"scenario1","type":"tag","displayName":"scenario1"},{"name":"Academy Choucair","type":"feature","displayName":"Academy Choucair"},{"name":"stories","type":"tag","displayName":"stories"}],"startTime":"2021-07-21T23:40:24.933-05:00[America/Bogota]","duration":28899,"testFailureCause":{"errorType":"net.thucydides.core.webdriver.exceptions.ElementShouldBeEnabledException","message":"Expected enabled element was not enabled","stackTrace":[{"declaringClass":"co.com.choucair.certification.proyecto1.tasks.Search","methodName":"performAs","fileName":"Search.java","lineNumber":25},{"declaringClass":"co.com.choucair.certification.proyecto1.stepdefinitions.ChoucairAcademyStepDefinitions","methodName":"sheSearchForTheCourseRecursosAutomatizacionBancolombiaOnTheChaucairAcademyPlatform","fileName":"ChoucairAcademyStepDefinitions.java","lineNumber":28},{"declaringClass":"cucumber.runner.Runner","methodName":"runPickle","fileName":"Runner.java","lineNumber":80}],"rootCause":{"errorType":"org.openqa.selenium.TimeoutException","message":"Expected condition failed: waiting for By.id: coursesearchbox to be enabled (tried for 5 second(s) with 100 milliseconds interval)","stackTrace":[{"declaringClass":"co.com.choucair.certification.proyecto1.tasks.Search","methodName":"performAs","fileName":"Search.java","lineNumber":25},{"declaringClass":"co.com.choucair.certification.proyecto1.stepdefinitions.ChoucairAcademyStepDefinitions","methodName":"sheSearchForTheCourseRecursosAutomatizacionBancolombiaOnTheChaucairAcademyPlatform","fileName":"ChoucairAcademyStepDefinitions.java","lineNumber":28},{"declaringClass":"cucumber.runner.Runner","methodName":"runPickle","fileName":"Runner.java","lineNumber":80}],"rootCause":{"errorType":"org.openqa.selenium.NoSuchElementException","message":"no such element: Unable to locate element: {\"method\":\"css selector\",\"selector\":\"#coursesearchbox\"}\n  (Session info: chrome\u003d92.0.4515.107)\nFor documentation on this error, please visit: https://www.seleniumhq.org/exceptions/no_such_element.html\nBuild info: version: \u00273.141.59\u0027, revision: \u0027e82be7d358\u0027, time: \u00272018-11-14T08:17:03\u0027\nSystem info: host: \u0027SOPORTE_WEB\u0027, ip: \u0027172.26.64.1\u0027, os.name: \u0027Windows 10\u0027, os.arch: \u0027amd64\u0027, os.version: \u002710.0\u0027, java.version: \u00271.8.0_231\u0027\nDriver info: org.openqa.selenium.chrome.ChromeDriver\nCapabilities {acceptInsecureCerts: false, browserName: chrome, browserVersion: 92.0.4515.107, chrome: {chromedriverVersion: 92.0.4515.43 (8c61b7e2989f2..., userDataDir: C:\\Users\\DITOSA~1\\AppData\\L...}, goog:chromeOptions: {debuggerAddress: localhost:55690}, javascriptEnabled: true, networkConnectionEnabled: false, pageLoadStrategy: normal, platform: WINDOWS, platformName: WINDOWS, proxy: Proxy(), setWindowRect: true, strictFileInteractability: false, timeouts: {implicit: 0, pageLoad: 300000, script: 30000}, unhandledPromptBehavior: dismiss and notify, webauthn:extension:credBlob: true, webauthn:extension:largeBlob: true, webauthn:virtualAuthenticators: true}\nSession ID: dc7412c25d1b2d013648faf9aefe75d9\n*** Element info: {Using\u003did, value\u003dcoursesearchbox}","stackTrace":[{"declaringClass":"co.com.choucair.certification.proyecto1.tasks.Search","methodName":"performAs","fileName":"Search.java","lineNumber":25},{"declaringClass":"co.com.choucair.certification.proyecto1.stepdefinitions.ChoucairAcademyStepDefinitions","methodName":"sheSearchForTheCourseRecursosAutomatizacionBancolombiaOnTheChaucairAcademyPlatform","fileName":"ChoucairAcademyStepDefinitions.java","lineNumber":28},{"declaringClass":"cucumber.runner.Runner","methodName":"runPickle","fileName":"Runner.java","lineNumber":80}]}}},"testFailureClassname":"net.thucydides.core.webdriver.exceptions.ElementShouldBeEnabledException","testFailureMessage":"Expected enabled element was not enabled","testFailureSummary":"FAILURE;net.thucydides.core.webdriver.exceptions.ElementShouldBeEnabledException;Expected enabled element was not enabled;Search.java","projectKey":"","annotatedResult":"FAILURE","sessionId":"dc7412c25d1b2d013648faf9aefe75d9","driver":"chrome:cindy","isManualTestingUpToDate":false,"manual":false,"testSource":"Cucumber","actors":[{"name":"Cindy","can":["browse the web"]}],"result":"FAILURE"}